{
  "checked": "no",
  "filename": "WKAPL00199000532",
  "validated_json": {
    "header": {
      "street": "Ruysdaelkade",
      "house_number": "1 hoog",
      "codenummer": 1578,
      "buurtletter": "AB",
      "stemdistrict_nr": "01-26"
    },
    "main_entries": [
      {
        "record_no": 1,
        "datum_registration": "P20337",
        "gezinshoofd": "van Horn, Franciscus F A",
        "year_of_birth": 87,
        "M": 1,
        "V": 0,
        "datum_vertrek": "090672",
        "waarheen": "Keizersgct. 647/629",
        "remarks": "le Helmersstr 309 II"
      },
      {
        "record_no": 2,
        "datum_registration": "",
        "gezinshoofd": "Sprey, Francisca E",
        "year_of_birth": 46,
        "M": 0,
        "V": 1,
        "datum_vertrek": "",
        "waarheen": "",
        "remarks": ""
      }
    ],
    "follow_up_entries": [
      {
        "volg_nr": 1,
        "datum": "",
        "inwonenden": "wed. van Horn, Muller, Otto-lina P",
        "year_of_birth": 18,
        "M": 0,
        "V": 1,
        "datum_vertrek": "101056",
        "waarheen": "P Potterstr 16 hs",
        "remarks": "Kalkoenstr 30 hs"
      },
      {
        "volg_nr": 2,
        "datum": "160751",
        "inwonenden": "Besteman, Johannes J",
        "year_of_birth": 25,
        "M": 1,
        "V": 0,
        "datum_vertrek": "150653",
        "waarheen": "Dirk Bonsstr 27 III",
        "remarks": "Kalverstr 78 hs"
      },
      {
        "volg_nr": 3,
        "datum": "060554",
        "inwonenden": "Wittveen, Trijntje",
        "year_of_birth": 26,
        "M": 0,
        "V": 1,
        "datum_vertrek": "ab",
        "waarheen": "zie regel lager",
        "remarks": "Sloterkade 84 hs"
      },
      {
        "volg_nr": 4,
        "datum": "300554",
        "inwonenden": "Halman, Anthonius J",
        "year_of_birth": 24,
        "M": 1,
        "V": 0,
        "datum_vertrek": "308060",
        "waarheen": "Hlm",
        "remarks": "Churchill-ln 223hs"
      },
      {
        "volg_nr": 5,
        "datum": "221253",
        "inwonenden": "Brekelmans, Jeannette H",
        "year_of_birth": 34,
        "M": 0,
        "V": 1,
        "datum_vertrek": "310354",
        "waarheen": "le vSwindenstr 117",
        "remarks": "Amstelk 36 III"
      },
      {
        "volg_nr": 6,
        "datum": "250451",
        "inwonenden": "Brouwer, Marchienis W",
        "year_of_birth": 20,
        "M": 0,
        "V": 1,
        "datum_vertrek": "ab",
        "waarheen": "abusief, zie III v",
        "remarks": ""
      },
      {
        "volg_nr": 7,
        "datum": "050554",
        "inwonenden": "Nijland, Pieterke",
        "year_of_birth": 24,
        "M": 0,
        "V": 1,
        "datum_vertrek": "281255",
        "waarheen": "Damstr. 26 I",
        "remarks": "Fr Halstgr. 9 III"
      },
      {
        "volg_nr": 8,
        "datum": "070256",
        "inwonenden": "Jacobi, Else M",
        "year_of_birth": 28,
        "M": 0,
        "V": 1,
        "datum_vertrek": "150562",
        "waarheen": "Niersstr 42 III",
        "remarks": "Grimburgwal 10"
      },
      {
        "volg_nr": 9,
        "datum": "091254",
        "inwonenden": "de Smit, Anna H",
        "year_of_birth": 28,
        "M": 0,
        "V": 1,
        "datum_vertrek": "200456",
        "waarheen": "Nedean Gld",
        "remarks": "Rooseveltlaan 169 III"
      },
      {
        "volg_nr": 10,
        "datum": "091254",
        "inwonenden": "Hart, Mara G",
        "year_of_birth": 28,
        "M": 0,
        "V": 1,
        "datum_vertrek": "200456",
        "waarheen": "Amstelkd 75 hs",
        "remarks": "Plantage Muidergr"
      },
      {
        "volg_nr": 11,
        "datum": "091254",
        "inwonenden": "Frigge, Adrianus L G",
        "year_of_birth": 28,
        "M": 1,
        "V": 0,
        "datum_vertrek": "200456",
        "waarheen": "Gelegenstr 51",
        "remarks": "Amstelkade 182 hs"
      },
      {
        "volg_nr": 12,
        "datum": "510660",
        "inwonenden": "Eichholtz, Marie L A",
        "year_of_birth": 28,
        "M": 0,
        "V": 1,
        "datum_vertrek": "200456",
        "waarheen": "A v IJmertstr 109",
        "remarks": "Blamendaal"
      },
      {
        "volg_nr": 13,
        "datum": "200263",
        "inwonenden": "Bakker, Bartholomeus J",
        "year_of_birth": 28,
        "M": 1,
        "V": 0,
        "datum_vertrek": "200456",
        "waarheen": "Oudorpper Ban 297",
        "remarks": "Transvaalstr 70 I"
      },
      {
        "volg_nr": 14,
        "datum": "200263",
        "inwonenden": "Fast, Helene",
        "year_of_birth": 28,
        "M": 0,
        "V": 1,
        "datum_vertrek": "180464",
        "waarheen": "Ruysdaelstr 70 III",
        "remarks": "Voorst"
      },
      {
        "volg_nr": 15,
        "datum": "040664",
        "inwonenden": "Wasanders, Albertha",
        "year_of_birth": 28,
        "M": 0,
        "V": 1,
        "datum_vertrek": "230565",
        "waarheen": "Bussum",
        "remarks": "Bussum"
      },
      {
        "volg_nr": 16,
        "datum": "040664",
        "inwonenden": "echtr Tromkamp, Berkhout, Margot A",
        "year_of_birth": 28,
        "M": 0,
        "V": 1,
        "datum_vertrek": "230565",
        "waarheen": "Bussum",
        "remarks": "Bussum"
      },
      {
        "volg_nr": 17,
        "datum": "040664",
        "inwonenden": "van Woerarden, Jans W V",
        "year_of_birth": 28,
        "M": 0,
        "V": 1,
        "datum_vertrek": "230565",
        "waarheen": "Utrechtstr 57 I",
        "remarks": "Zenkum"
      },
      {
        "volg_nr": 18,
        "datum": "190595",
        "inwonenden": "Jonkman, Paul H",
        "year_of_birth": 42,
        "M": 1,
        "V": 0,
        "datum_vertrek": "230565",
        "waarheen": "Ruysdaelkd 4. III a",
        "remarks": "Grasrijp 9 hs"
      },
      {
        "volg_nr": 19,
        "datum": "251066",
        "inwonenden": "Benes, Dienke",
        "year_of_birth": 44,
        "M": 0,
        "V": 1,
        "datum_vertrek": "151068",
        "waarheen": "Gron",
        "remarks": "De Lairessestraat 3"
      }
    ],
    "footer_notes": ""
  },
  "error": null,
  "tokens": {
    "input": 1545,
    "output": 2015,
    "total_cost_usd": 0.012006
  },
  "finish_reason": "stop",
  "image_url": "../processed_images/WKAPL00199000532.jpg"
}