{
  "checked": "no",
  "filename": "WKAPL00052000852",
  "validated_json": null,
  "error": "15 validation errors for Woningkaart\nmain_entries.3.datum_registration\n  Input should be a valid string [type=string_type, input_value=131157, input_type=int]\n    For further information visit https://errors.pydantic.dev/2.11/v/string_type\nmain_entries.3.datum_vertrek\n  Input should be a valid string [type=string_type, input_value=311059, input_type=int]\n    For further information visit https://errors.pydantic.dev/2.11/v/string_type\nmain_entries.4.datum_registration\n  Input should be a valid string [type=string_type, input_value=100558, input_type=int]\n    For further information visit https://errors.pydantic.dev/2.11/v/string_type\nmain_entries.4.datum_vertrek\n  Input should be a valid string [type=string_type, input_value=290758, input_type=int]\n    For further information visit https://errors.pydantic.dev/2.11/v/string_type\nmain_entries.5.datum_registration\n  Input should be a valid string [type=string_type, input_value=110858, input_type=int]\n    For further information visit https://errors.pydantic.dev/2.11/v/string_type\nmain_entries.5.datum_vertrek\n  Input should be a valid string [type=string_type, input_value=130958, input_type=int]\n    For further information visit https://errors.pydantic.dev/2.11/v/string_type\nmain_entries.6.datum_registration\n  Input should be a valid string [type=string_type, input_value=120858, input_type=int]\n    For further information visit https://errors.pydantic.dev/2.11/v/string_type\nmain_entries.6.datum_vertrek\n  Input should be a valid string [type=string_type, input_value=310959, input_type=int]\n    For further information visit https://errors.pydantic.dev/2.11/v/string_type\nmain_entries.7.datum_registration\n  Input should be a valid string [type=string_type, input_value=230459, input_type=int]\n    For further information visit https://errors.pydantic.dev/2.11/v/string_type\nmain_entries.7.datum_vertrek\n  Input should be a valid string [type=string_type, input_value=310763, input_type=int]\n    For further information visit https://errors.pydantic.dev/2.11/v/string_type\nmain_entries.8.datum_registration\n  Input should be a valid string [type=string_type, input_value=110762, input_type=int]\n    For further information visit https://errors.pydantic.dev/2.11/v/string_type\nmain_entries.8.datum_vertrek\n  Input should be a valid string [type=string_type, input_value=311062, input_type=int]\n    For further information visit https://errors.pydantic.dev/2.11/v/string_type\nmain_entries.9.datum_registration\n  Input should be a valid string [type=string_type, input_value=131163, input_type=int]\n    For further information visit https://errors.pydantic.dev/2.11/v/string_type\nmain_entries.10.datum_registration\n  Input should be a valid string [type=string_type, input_value=909365, input_type=int]\n    For further information visit https://errors.pydantic.dev/2.11/v/string_type\nmain_entries.10.datum_vertrek\n  Input should be a valid string [type=string_type, input_value=101067, input_type=int]\n    For further information visit https://errors.pydantic.dev/2.11/v/string_type",
  "raw_json": "{\"header\": {\"street\": \"Kuipersstraat\", \"house_number\": \"19\", \"codenummer\": 979, \"buurtletter\": \"AF\", \"stemdistrict_nr\": \"01-271\"}, \"main_entries\": [{\"record_no\": 1, \"datum_registration\": \"\", \"gezinshoofd\": \"Voor hoofdbewoner zie kaartje 10\", \"year_of_birth\": null, \"M\": null, \"V\": null, \"datum_vertrek\": \"\", \"waarheen\": \"(W van Zeeland) (van Schaik Zillesen, Elsje)\", \"remarks\": \"(L A Schilt) (Geerink, Arend)\"}, {\"record_no\": 2, \"datum_registration\": \"\", \"gezinshoofd\": \"idem\", \"year_of_birth\": null, \"M\": null, \"V\": null, \"datum_vertrek\": \"\", \"waarheen\": \"\", \"remarks\": \"\"}, {\"record_no\": 3, \"datum_registration\": \"\", \"gezinshoofd\": \"idem\", \"year_of_birth\": null, \"M\": null, \"V\": null, \"datum_vertrek\": \"\", \"waarheen\": \"\", \"remarks\": \"\"}, {\"record_no\": 4, \"datum_registration\": 131157, \"gezinshoofd\": \"van Kesteren, Astrid M\", \"year_of_birth\": 1959, \"M\": 0, \"V\": 1, \"datum_vertrek\": 311059, \"waarheen\": \"Haarl. Iedec Q.\", \"remarks\": \"G. Flinkstr. 243 I-V\"}, {\"record_no\": 5, \"datum_registration\": 100558, \"gezinshoofd\": \"Huijer, Willem\", \"year_of_birth\": 1925, \"M\": 1, \"V\": 0, \"datum_vertrek\": 290758, \"waarheen\": \"Vrolikstr. 154 II\", \"remarks\": \"Swammerd. str. 21 I\"}, {\"record_no\": 6, \"datum_registration\": 110858, \"gezinshoofd\": \"Wieten, Herman B\", \"year_of_birth\": 1928, \"M\": 1, \"V\": 0, \"datum_vertrek\": 130958, \"waarheen\": \"Rembrandtsplein 24hs\", \"remarks\": \"Comeniusstr. 2\"}, {\"record_no\": 7, \"datum_registration\": 120858, \"gezinshoofd\": \"Swart, Hans\", \"year_of_birth\": 1930, \"M\": 1, \"V\": 0, \"datum_vertrek\": 310959, \"waarheen\": \"Bred. Hendrikstr. 188\", \"remarks\": \"H. Muidergt. nr hs\"}, {\"record_no\": 8, \"datum_registration\": 230459, \"gezinshoofd\": \"van Houtum, Albertus W\", \"year_of_birth\": 1927, \"M\": 1, \"V\": 0, \"datum_vertrek\": 310763, \"waarheen\": \"naar 19 II\", \"remarks\": \"Berchem (BE)\"}, {\"record_no\": 9, \"datum_registration\": 110762, \"gezinshoofd\": \"van der Wolf, Willem\", \"year_of_birth\": 1924, \"M\": 1, \"V\": 0, \"datum_vertrek\": 311062, \"waarheen\": \"Groot-Brittannië\", \"remarks\": \"Hoofdweg 144 II\"}, {\"record_no\": 10, \"datum_registration\": 131163, \"gezinshoofd\": \"Schilt, Louise A\", \"year_of_birth\": 1934, \"M\": 0, \"V\": 1, \"datum_vertrek\": \"\", \"waarheen\": \"zie krt 1 gezin 2\", \"remarks\": \"Amstel 326 II\"}, {\"record_no\": 11, \"datum_registration\": 909365, \"gezinshoofd\": \"Zwaan, Anne\", \"year_of_birth\": 1947, \"M\": 0, \"V\": 1, \"datum_vertrek\": 101067, \"waarheen\": \"v. Eghenstr. 46 II\", \"remarks\": \"Anske Lammingastr. 13\"}, {\"record_no\": 12, \"datum_registration\": \"\", \"gezinshoofd\": \"Schilt, Louise A\", \"year_of_birth\": 1934, \"M\": 0, \"V\": 1, \"datum_vertrek\": \"\", \"waarheen\": \"zie krt 1 gezin 6\", \"remarks\": \"\"}], \"follow_up_entries\": [], \"footer_notes\": \"\"}",
  "tokens": {
    "input": 1545,
    "output": 1168,
    "total_cost_usd": 0.007771
  },
  "finish_reason": "stop",
  "image_url": "../processed_images/WKAPL00052000852.jpg"
}