{
  "filename": "WKAPL00023000385",
  "validated_json": {
    "header": {
      "street": "Andersensingel",
      "house_number": "",
      "codenummer": 35152,
      "buurtletter": "DB",
      "stemdistrict_nr": "2"
    },
    "main_entries": [
      {
        "record_no": 1,
        "datum_registration": "060384",
        "gezinshoofd": "Van Daele, Bernard J",
        "year_of_birth": 44,
        "M": 1,
        "V": 0,
        "datum_vertrek": "",
        "waarheen": "",
        "remarks": ""
      },
      {
        "record_no": 2,
        "datum_registration": "060384",
        "gezinshoofd": "Gersen, Maria C E",
        "year_of_birth": 44,
        "M": 0,
        "V": 1,
        "datum_vertrek": "",
        "waarheen": "",
        "remarks": ""
      }
    ],
    "follow_up_entries": [],
    "footer_notes": ""
  },
  "error": null,
  "tokens": {
    "input": 1545,
    "output": 230,
    "total_cost_usd": 0.003081
  },
  "finish_reason": "stop",
  "_url": "https://drive.google.com/uc?export=view&id=1khwZ0AW2HwZvTQRMB_NdUBonaRGligs5"
}