{
  "filename": "WKAPL00256001224",
  "validated_json": {
    "header": {
      "street": "Laagte Kadijk",
      "house_number": "",
      "codenummer": 139,
      "buurtletter": "G",
      "stemdistrict_nr": ""
    },
    "main_entries": [
      {
        "record_no": 1,
        "datum_registration": "151286",
        "gezinshoofd": "van Hoboken, Johanna J A M",
        "year_of_birth": 53,
        "M": 0,
        "V": 1,
        "datum_vertrek": "",
        "waarheen": "",
        "remarks": ""
      }
    ],
    "follow_up_entries": [],
    "footer_notes": ""
  },
  "error": null,
  "tokens": {
    "input": 1545,
    "output": 153,
    "total_cost_usd": 0.002696
  },
  "finish_reason": "stop",
  "_url": "https://drive.google.com/uc?export=view&id=1o5OzLMMzDIhYtl0L7nfOWpC3Pbq7_JPz"
}